{"commit_hash": "c160aedc46ebb8e41921cc6465f1b827a5b74914", "env_name": "virtualenv-py3.10-Cython-build-packaging", "date": 1728584116000, "params": {"machine": "gh-runner", "python": "3.10", "Cython": "", "build": "", "packaging": ""}, "python": "3.10", "requirements": {"Cython": "", "build": "", "packaging": ""}, "env_vars": {}, "result_columns": ["result", "params", "version", "started_at", "duration", "stats_ci_99_a", "stats_ci_99_b", "stats_q_25", "stats_q_75", "stats_number", "stats_repeat", "samples", "profile"], "results": {"benchmarks.time_feature_creation": [[0.13393805199996223], [], "6974001c81e398eadda4614d6cfde75a8bfab65d8cb8763ac4a02ce8ac661b13", 1728584218274, 1.6723, [0.13142], [0.13706], [0.13299], [0.13479], [1], [10]], "benchmarks.time_learn_loop": [[2.6212908585000037, 2.660874570499999, 0.16360574550000706, 0.17000905999998395], [["'RandomForest'", "'KNN'"], ["'RandomSampling'", "'UncSampling'"]], "144671bba6ade43fa4a7abc9b5c4c5d8add5fd9c0e53513f26ef01b144ef1b92", 1728584219124, 47.037, [2.6028, 2.6042, 0.1618, 0.16586], [2.6385, 2.7026, 0.16843, 0.17066], [2.6173, 2.6558, 0.16322, 0.16703], [2.6292, 2.6752, 0.16479, 0.17043], [1, 1, 1, 1], [6, 6, 10, 10]], "benchmarks.peakmem_learn_loop": [[168456192, 172736512], [["'RandomForest'", "'KNN'"]], "e250760594849f074601db4bcd5ad80bf9671afb0adc3f02f544b7b83db53cf6", 1728587946186, 2.9565]}, "durations": {"<build>": 3.507840156555176}, "version": 2}